{"code": 0, "msg": "success", "date": "2020-12-29", "support_url": "https://logi.im", "sentences": [{"api": "hici", "sentence": "Everything's changed. My life will never be the same.", "translation": "\u6240\u6709\u7684\u4e8b\u60c5\u90fd\u6539\u53d8\u4e86\uff0c\u6211\u7684\u751f\u547d\u5b8c\u5168\u4e0d\u4e00\u6837\u4e86\u3002", "source": "\u5f71\u7247\u300a\u98ce\u96e8\u54c8\u4f5b\u8def\u300b"}, {"api": "shanbay", "sentence": "Expect the best. Prepare for the worst. Capitalize on what comes.", "translation": "\u8981\u62b1\u6700\u5927\u7684\u5e0c\u671b\uff0c\u505a\u6700\u574f\u7684\u6253\u7b97\uff0c\u4ece\u7ed3\u679c\u4e2d\u5b66\u4e60\u3002", "source": "Zig Ziglar"}, {"api": "ciba", "sentence": "Travel can be one of the most rewarding forms of introspection.", "translation": "\u65c5\u884c\u53ef\u80fd\u662f\u6700\u6709\u76ca\u7684\u81ea\u7701\u65b9\u5f0f\u4e4b\u4e00\u3002", "source": null}, {"api": "youdao", "sentence": "None of us is perfect forever.", "translation": "\u6ca1\u6709\u4eba\u662f\u6c38\u8fdc\u5b8c\u7f8e\u65e0\u7455\u7684\u3002", "source": "\u300a\u672c\u6770\u660e\u00b7\u5df4\u987f\u5947\u4e8b\u300b"}, {"api": "eudic", "sentence": "Trees made shadows over the pond, and water plants grew at the deep end.", "translation": "\u6811\u5f71\u5012\u6620\u5728\u5858\u4e2d\uff0c\u6df1\u6c34\u4e2d\u957f\u7740\u6c34\u8349\u3002", "source": null}]}